pyresolver/__init__.py
pyresolver/_exception_helper.py
pyresolver/_ioc.py
pyresolver/_ioc_base.py
pyresolver/exceptions.py
pyresolver/interfaces.py
tests/__init__.py
tests/pyresolver/__init__.py
tests/pyresolver/test_base.py
pyresolver-0.0.3.dist-info/LICENSE.txt
pyresolver-0.0.3.dist-info/METADATA
pyresolver-0.0.3.dist-info/WHEEL
pyresolver-0.0.3.dist-info/top_level.txt
pyresolver-0.0.3.dist-info/RECORD
