Metadata-Version: 2.1
Name: pyresolver
Version: 0.0.3
Summary: Cool IoC container
Home-page: https://github.com/zaryanezrya/pyresolver
Author: Ivan Sharun
Author-email: ivan@sha.run
License: MIT
Project-URL: Source, https://github.com/zaryanezrya/pyresolver
Keywords: IoC,Inversion of control,resolve
Platform: UNKNOWN
Classifier: Development Status :: 3 - Alpha
Classifier: Intended Audience :: Developers
Classifier: Topic :: Software Development :: Libraries
Classifier: License :: OSI Approved :: MIT License
Classifier: Programming Language :: Python :: 3.5
Classifier: Programming Language :: Python :: 3.6
Classifier: Programming Language :: Python :: 3.7
Classifier: Programming Language :: Python :: 3.8
Classifier: Programming Language :: Python :: 3.9
Classifier: Programming Language :: Python :: Implementation :: CPython
